{"is_source_file": true, "file_id": 20, "git_revision": "", "state": 1, "description": "", "external_files": [], "external_methods": [], "published": [], "classes": [], "methods": [], "calls": [], "search-terms": [], "ctags": [{"_type": "tag", "name": "router", "path": "/home/kavia/workspace/code-generation/mood-tracker-and-journal-284061-284072/mood_log_backend/src/routes/auth.routes.js", "pattern": "/^const router = Router();$/", "language": "JavaScript", "kind": "constant"}], "format": "JavaScript", "hash": "57891fea821b6c0297f383112ef614cd", "format-version": 4, "code-base-name": "mood_log_backend", "filename": "mood_log_backend/src/routes/auth.routes.js", "knowledge_revision": 34}